P3MLens/Plane.py
P3MLens/__init__.py
P3MLens-1.0.0.dist-info/LICENSE
P3MLens-1.0.0.dist-info/METADATA
P3MLens-1.0.0.dist-info/WHEEL
P3MLens-1.0.0.dist-info/top_level.txt
P3MLens-1.0.0.dist-info/RECORD
